{"AUSDT": "sell", "AAVEUSDT": "sell", "ADAUSDT": "sell", "AIXBTUSDT": "sell", "ALGOUSDT": "sell", "APTUSDT": "sell", "ARBUSDT": "sell", "ARKMUSDT": "sell", "ATOMUSDT": "sell", "AXSUSDT": "sell", "AVAXUSDT": "sell", "BCHUSDT": "sell", "BERAUSDT": "sell", "BIOUSDT": "sell", "BNBUSDT": "sell", "BONKUSDT": "sell", "BTCUSDT": "sell", "BTTCUSDT": "sell", "CAKEUSDT": "sell", "CETUSUSDT": "sell", "COOKIEUSDT": "sell", "CRVUSDT": "sell", "CVXUSDT": "sell", "DEXEUSDT": "buy", "DOGEUSDT": "sell", "DOTUSDT": "sell", "EIGENUSDT": "sell", "ENAUSDT": "sell", "ENSUSDT": "sell", "ETCUSDT": "sell", "ETHUSDT": "sell", "ETHFIUSDT": "sell", "FETUSDT": "sell", "FLOKIUSDT": "sell", "FLOWUSDT": "sell", "FORMUSDT": "sell", "GALAUSDT": "sell", "GRTUSDT": "sell", "HBARUSDT": "sell", "HUMAUSDT": "sell", "ICPUSDT": "sell", "IMXUSDT": "sell", "INITUSDT": "sell", "INJUSDT": "sell", "IOTAUSDT": "sell", "JASMYUSDT": "sell", "JTOUSDT": "sell", "JUPUSDT": "sell", "KAIAUSDT": "sell", "KAITOUSDT": "sell", "KERNELUSDT": "sell", "LDOUSDT": "sell", "LTCUSDT": "sell", "LINKUSDT": "sell", "MASKUSDT": "buy", "MKRUSDT": "sell", "MEUSDT": "sell", "MOVEUSDT": "sell", "NEARUSDT": "sell", "NEIROUSDT": "sell", "NEOUSDT": "sell", "NEXOUSDT": "sell", "NILUSDT": "buy", "NOTUSDT": "sell", "ONDOUSDT": "sell", "OPUSDT": "sell", "ORCAUSDT": "sell", "PAXGUSDT": "sell", "PENDLEUSDT": "sell", "PENGUUSDT": "sell", "PEPEUSDT": "sell", "POLUSDT": "sell", "PNUTUSDT": "sell", "PYTHUSDT": "sell", "QNTUSDT": "sell", "RAYUSDT": "sell", "RENDERUSDT": "sell", "RUNEUSDT": "sell", "SUSDT": "sell", "SANDUSDT": "sell", "SEIUSDT": "sell", "SHIBUSDT": "sell", "SOLUSDT": "sell", "SOPHUSDT": "sell", "SSVUSDT": "sell", "STXUSDT": "sell", "SUIUSDT": "sell", "TAOUSDT": "sell", "THETAUSDT": "sell", "TIAUSDT": "sell", "TONUSDT": "buy", "TNSRUSDT": "sell", "TRBUSDT": "buy", "TRUMPUSDT": "sell", "TRXUSDT": "sell", "UNIUSDT": "sell", "VETUSDT": "sell", "VIRTUALUSDT": "sell", "WCTUSDT": "buy", "WIFUSDT": "sell", "WLDUSDT": "sell", "XLMUSDT": "sell", "XRPUSDT": "sell", "ZECUSDT": "sell", "ZKUSDT": "sell", "ZROUSDT": "sell"}